adampy/__init__.py
adampy/adampy.py
adampy-0.0.10.dist-info/LICENSE
adampy-0.0.10.dist-info/METADATA
adampy-0.0.10.dist-info/WHEEL
adampy-0.0.10.dist-info/top_level.txt
adampy-0.0.10.dist-info/RECORD
