Metadata-Version: 2.1
Name: adampy
Version: 0.0.10
Summary: Python Adam API
Home-page: https://git.services.meeo.it/sistema/adampy
Author: MEEO s.r.l.
Author-email: info@meeo.it
License: UNKNOWN
Platform: UNKNOWN
Classifier: Programming Language :: Python :: 3
Classifier: License :: OSI Approved :: MIT License
Classifier: Operating System :: Unix
Requires-Python: >=3.6
Requires-Dist: numpy (>=1.17.2)
Requires-Dist: requests (>=2.18.4)
Requires-Dist: fiona (>=1.8.6)
Requires-Dist: imageio (>=2.5.0)
Requires-Dist: matplotlib (>=3.1.1)
Requires-Dist: geopandas (>=0.5.0)
Requires-Dist: xarray (>=0.13.0)
Requires-Dist: datetime (>=4.0)
Requires-Dist: rasterio (>=1.0.23)
